
{
  "header": {
    "reportVersion": 1,
    "event": "Allocation failed - JavaScript heap out of memory",
    "trigger": "FatalError",
    "filename": "report.20200211.124755.89765.0.001.json",
    "dumpEventTime": "2020-02-11T12:47:55Z",
    "dumpEventTimeStamp": "1581392875921",
    "processId": 89765,
    "cwd": "/Users/oguzgelal/Core/web/TOPTAL/marketmuse/mms-editor/example",
    "commandLine": [
      "node",
      "/Users/oguzgelal/Core/web/TOPTAL/marketmuse/mms-editor/example/node_modules/react-scripts/scripts/start.js"
    ],
    "nodejsVersion": "v12.10.0",
    "wordSize": 64,
    "arch": "x64",
    "platform": "darwin",
    "componentVersions": {
      "node": "12.10.0",
      "v8": "7.6.303.29-node.16",
      "uv": "1.31.0",
      "zlib": "1.2.11",
      "brotli": "1.0.7",
      "ares": "1.15.0",
      "modules": "72",
      "nghttp2": "1.39.2",
      "napi": "4",
      "llhttp": "1.1.4",
      "http_parser": "2.8.0",
      "openssl": "1.1.1c",
      "cldr": "35.1",
      "icu": "64.2",
      "tz": "2019a",
      "unicode": "12.1"
    },
    "release": {
      "name": "node",
      "headersUrl": "https://nodejs.org/download/release/v12.10.0/node-v12.10.0-headers.tar.gz",
      "sourceUrl": "https://nodejs.org/download/release/v12.10.0/node-v12.10.0.tar.gz"
    },
    "osName": "Darwin",
    "osRelease": "19.0.0",
    "osVersion": "Darwin Kernel Version 19.0.0: Wed Sep 25 20:18:50 PDT 2019; root:xnu-6153.11.26~2/RELEASE_X86_64",
    "osMachine": "x86_64",
    "cpus": [
      {
        "model": "Intel(R) Core(TM) i7-4558U CPU @ 2.80GHz",
        "speed": 2800,
        "user": 97500320,
        "nice": 0,
        "sys": 46786460,
        "idle": 234858660,
        "irq": 0
      },
      {
        "model": "Intel(R) Core(TM) i7-4558U CPU @ 2.80GHz",
        "speed": 2800,
        "user": 26483130,
        "nice": 0,
        "sys": 19923550,
        "idle": 332678040,
        "irq": 0
      },
      {
        "model": "Intel(R) Core(TM) i7-4558U CPU @ 2.80GHz",
        "speed": 2800,
        "user": 93915520,
        "nice": 0,
        "sys": 41408850,
        "idle": 243760430,
        "irq": 0
      },
      {
        "model": "Intel(R) Core(TM) i7-4558U CPU @ 2.80GHz",
        "speed": 2800,
        "user": 24555980,
        "nice": 0,
        "sys": 18326720,
        "idle": 336201860,
        "irq": 0
      }
    ],
    "networkInterfaces": [
      {
        "name": "lo0",
        "internal": true,
        "mac": "00:00:00:00:00:00",
        "address": "127.0.0.1",
        "netmask": "255.0.0.0",
        "family": "IPv4"
      },
      {
        "name": "lo0",
        "internal": true,
        "mac": "00:00:00:00:00:00",
        "address": "::1",
        "netmask": "ffff:ffff:ffff:ffff:ffff:ffff:ffff:ffff",
        "family": "IPv6",
        "scopeid": 0
      },
      {
        "name": "lo0",
        "internal": true,
        "mac": "00:00:00:00:00:00",
        "address": "fe80::1",
        "netmask": "ffff:ffff:ffff:ffff::",
        "family": "IPv6",
        "scopeid": 1
      },
      {
        "name": "en0",
        "internal": false,
        "mac": "78:31:c1:c1:cb:26",
        "address": "10.126.0.15",
        "netmask": "255.255.255.0",
        "family": "IPv4"
      },
      {
        "name": "awdl0",
        "internal": false,
        "mac": "0e:63:87:bd:78:5f",
        "address": "fe80::c63:87ff:febd:785f",
        "netmask": "ffff:ffff:ffff:ffff::",
        "family": "IPv6",
        "scopeid": 9
      },
      {
        "name": "llw0",
        "internal": false,
        "mac": "0e:63:87:bd:78:5f",
        "address": "fe80::c63:87ff:febd:785f",
        "netmask": "ffff:ffff:ffff:ffff::",
        "family": "IPv6",
        "scopeid": 10
      },
      {
        "name": "utun0",
        "internal": false,
        "mac": "00:00:00:00:00:00",
        "address": "fe80::b024:d164:c37d:5531",
        "netmask": "ffff:ffff:ffff:ffff::",
        "family": "IPv6",
        "scopeid": 11
      },
      {
        "name": "utun1",
        "internal": false,
        "mac": "00:00:00:00:00:00",
        "address": "fe80::1e0a:4dbd:7140:f865",
        "netmask": "ffff:ffff:ffff:ffff::",
        "family": "IPv6",
        "scopeid": 12
      },
      {
        "name": "utun2",
        "internal": false,
        "mac": "00:00:00:00:00:00",
        "address": "fe80::d191:1ccd:9048:3ea1",
        "netmask": "ffff:ffff:ffff:ffff::",
        "family": "IPv6",
        "scopeid": 13
      },
      {
        "name": "utun3",
        "internal": false,
        "mac": "00:00:00:00:00:00",
        "address": "fe80::1dd5:14d5:64aa:119f",
        "netmask": "ffff:ffff:ffff:ffff::",
        "family": "IPv6",
        "scopeid": 14
      },
      {
        "name": "utun4",
        "internal": false,
        "mac": "00:00:00:00:00:00",
        "address": "fe80::7816:c322:5be9:b071",
        "netmask": "ffff:ffff:ffff:ffff::",
        "family": "IPv6",
        "scopeid": 15
      },
      {
        "name": "utun5",
        "internal": false,
        "mac": "00:00:00:00:00:00",
        "address": "fe80::89ea:9ff4:3580:e313",
        "netmask": "ffff:ffff:ffff:ffff::",
        "family": "IPv6",
        "scopeid": 16
      }
    ],
    "host": "Oguzs-Macbook-Pro.local"
  },
  "javascriptStack": {
    "message": "No stack.",
    "stack": [
      "Unavailable."
    ]
  },
  "nativeStack": [
    {
      "pc": "0x00000001001461d0",
      "symbol": "report::TriggerNodeReport(v8::Isolate*, node::Environment*, char const*, char const*, std::__1::basic_string<char, std::__1::char_traits<char>, std::__1::allocator<char> > const&, v8::Local<v8::String>) [/usr/local/bin/node]"
    },
    {
      "pc": "0x0000000100078d95",
      "symbol": "node::OnFatalError(char const*, char const*) [/usr/local/bin/node]"
    },
    {
      "pc": "0x000000010016e8d7",
      "symbol": "v8::Utils::ReportOOMFailure(v8::internal::Isolate*, char const*, bool) [/usr/local/bin/node]"
    },
    {
      "pc": "0x000000010016e873",
      "symbol": "v8::internal::V8::FatalProcessOutOfMemory(v8::internal::Isolate*, char const*, bool) [/usr/local/bin/node]"
    },
    {
      "pc": "0x00000001002f2605",
      "symbol": "v8::internal::Heap::FatalProcessOutOfMemory(char const*) [/usr/local/bin/node]"
    },
    {
      "pc": "0x00000001002f3d2d",
      "symbol": "v8::internal::Heap::RecomputeLimits(v8::internal::GarbageCollector) [/usr/local/bin/node]"
    },
    {
      "pc": "0x00000001002f0ae6",
      "symbol": "v8::internal::Heap::PerformGarbageCollection(v8::internal::GarbageCollector, v8::GCCallbackFlags) [/usr/local/bin/node]"
    },
    {
      "pc": "0x00000001002eea3c",
      "symbol": "v8::internal::Heap::CollectGarbage(v8::internal::AllocationSpace, v8::internal::GarbageCollectionReason, v8::GCCallbackFlags) [/usr/local/bin/node]"
    },
    {
      "pc": "0x00000001002fa114",
      "symbol": "v8::internal::Heap::AllocateRawWithLightRetry(int, v8::internal::AllocationType, v8::internal::AllocationAlignment) [/usr/local/bin/node]"
    },
    {
      "pc": "0x00000001002fa18f",
      "symbol": "v8::internal::Heap::AllocateRawWithRetryOrFail(int, v8::internal::AllocationType, v8::internal::AllocationAlignment) [/usr/local/bin/node]"
    },
    {
      "pc": "0x00000001002caaaa",
      "symbol": "v8::internal::Factory::NewRawOneByteString(int, v8::internal::AllocationType) [/usr/local/bin/node]"
    },
    {
      "pc": "0x00000001005088b2",
      "symbol": "v8::internal::String::SlowFlatten(v8::internal::Isolate*, v8::internal::Handle<v8::internal::ConsString>, v8::internal::AllocationType) [/usr/local/bin/node]"
    },
    {
      "pc": "0x0000000100629758",
      "symbol": "v8::internal::Runtime_StringCharCodeAt(int, unsigned long*, v8::internal::Isolate*) [/usr/local/bin/node]"
    },
    {
      "pc": "0x00000001009288f9",
      "symbol": "Builtins_CEntry_Return1_DontSaveFPRegs_ArgvOnStack_NoBuiltinExit [/usr/local/bin/node]"
    },
    {
      "pc": "0x00002d76b95829de",
      "symbol": ""
    }
  ],
  "javascriptHeap": {
    "totalMemory": 2160963584,
    "totalCommittedMemory": 2158395264,
    "usedMemory": 1882191128,
    "availableMemory": 122401448,
    "memoryLimit": 2197815296,
    "heapSpaces": {
      "read_only_space": {
        "memorySize": 262144,
        "committedMemory": 31744,
        "capacity": 261832,
        "used": 31432,
        "available": 230400
      },
      "new_space": {
        "memorySize": 33554432,
        "committedMemory": 31721520,
        "capacity": 16757248,
        "used": 2008080,
        "available": 14749168
      },
      "old_space": {
        "memorySize": 2032775168,
        "committedMemory": 2032566712,
        "capacity": 1841508704,
        "used": 1787695784,
        "available": 53812920
      },
      "code_space": {
        "memorySize": 2523136,
        "committedMemory": 2227616,
        "capacity": 1835456,
        "used": 1835456,
        "available": 0
      },
      "map_space": {
        "memorySize": 3674112,
        "committedMemory": 3673080,
        "capacity": 2642720,
        "used": 2642720,
        "available": 0
      },
      "large_object_space": {
        "memorySize": 87552000,
        "committedMemory": 87552000,
        "capacity": 87427096,
        "used": 87427096,
        "available": 0
      },
      "code_large_object_space": {
        "memorySize": 622592,
        "committedMemory": 622592,
        "capacity": 550560,
        "used": 550560,
        "available": 0
      },
      "new_large_object_space": {
        "memorySize": 0,
        "committedMemory": 0,
        "capacity": 16757248,
        "used": 0,
        "available": 16757248
      }
    }
  },
  "resourceUsage": {
    "userCpuSeconds": 598.73,
    "kernelCpuSeconds": 179.479,
    "cpuConsumptionPercent": 2.6124,
    "maxRss": 2475662770176,
    "pageFaults": {
      "IORequired": 463,
      "IONotRequired": 5284472
    },
    "fsActivity": {
      "reads": 0,
      "writes": 0
    }
  },
  "libuv": [
  ],
  "environmentVariables": {
    "NODE": "/usr/local/bin/node",
    "npm_config_version_git_tag": "true",
    "INIT_CWD": "/Users/oguzgelal/Core/web/TOPTAL/marketmuse/mms-editor/example",
    "TERM": "xterm-256color",
    "SHELL": "/bin/zsh",
    "npm_config__bit_registry": "https://node.bitsrc.io",
    "npm_config_init_license": "MIT",
    "npm_config_registry": "https://registry.yarnpkg.com",
    "npm_package_private": "true",
    "npm_package_dependencies_react_dom": "file:../node_modules/react-dom",
    "npm_package_readmeFilename": "README.md",
    "npm_config_python": "/usr/bin/python",
    "npm_package_description": "In the project directory, you can run:",
    "USER": "root",
    "npm_package_dependencies__testing_library_user_event": "^7.1.2",
    "SUDO_USER": "oguzgelal",
    "npm_package_browserslist_development_1": "last 1 firefox version",
    "SUDO_UID": "501",
    "npm_package_browserslist_development_0": "last 1 chrome version",
    "npm_package_eslintConfig_extends": "react-app",
    "SSH_AUTH_SOCK": "/private/tmp/com.apple.launchd.e8XtDUBEbo/Listeners",
    "npm_package_browserslist_development_2": "last 1 safari version",
    "__CF_USER_TEXT_ENCODING": "0x0:0:0",
    "npm_execpath": "/usr/local/Cellar/yarn/1.10.1/libexec/bin/yarn.js",
    "USERNAME": "root",
    "LSCOLORS": "Gxfxcxdxbxegedabagacad",
    "npm_config_argv": "{\"remain\":[],\"cooked\":[\"run\",\"start\"],\"original\":[\"run\",\"start\"]}",
    "PATH": "/Users/oguzgelal/Core/web/TOPTAL/marketmuse/mms-editor/example/node_modules/.bin:/usr/local/share/.config/yarn/link/node_modules/.bin:/Users/oguzgelal/Core/web/TOPTAL/marketmuse/mms-editor/example/node_modules/.bin:/usr/local/share/.config/yarn/link/node_modules/.bin:/usr/local/libexec/lib/node_modules/npm/bin/node-gyp-bin:/usr/local/lib/node_modules/npm/bin/node-gyp-bin:/usr/local/bin/node_modules/npm/bin/node-gyp-bin:/Users/oguzgelal/.pyenv/shims:/Users/oguzgelal/bin:/usr/local/bin:/usr/local/bin:/usr/bin:/bin:/usr/sbin:/sbin:/usr/local/sbin:/usr/local/mongodb/bin:/Users/oguzgelal/.local/bin:/Users/oguzgelal/Library/Python/3.7/bin",
    "MAIL": "/var/mail/root",
    "npm_package_browserslist_production_1": "not dead",
    "npm_package_browserslist_production_0": ">0.2%",
    "PWD": "/Users/oguzgelal/Core/web/TOPTAL/marketmuse/mms-editor/example",
    "npm_package_browserslist_production_2": "not op_mini all",
    "npm_lifecycle_event": "start",
    "npm_package_name": "example",
    "LANG": "en_CA.UTF-8",
    "npm_config_version_commit_hooks": "true",
    "npm_package_scripts_start": "react-scripts start",
    "npm_package_scripts_build": "react-scripts build",
    "npm_config_bin_links": "true",
    "npm_package_version": "0.1.0",
    "HOME": "/Users/oguzgelal",
    "SUDO_COMMAND": "/usr/local/bin/yarn run start",
    "SHLVL": "1",
    "npm_package_scripts_test": "react-scripts test",
    "npm_config_strict_ssl": "true",
    "npm_config_save_prefix": "^",
    "npm_config_version_git_message": "v%s",
    "npm_package_dependencies__testing_library_jest_dom": "^4.2.4",
    "NPM_CONFIG_PYTHON": "/usr/bin/python",
    "npm_package_dependencies_react_scripts": "3.3.0",
    "YARN_WRAP_OUTPUT": "false",
    "LOGNAME": "root",
    "npm_lifecycle_script": "react-scripts start",
    "PREFIX": "/usr/local",
    "npm_package_dependencies_react": "file:../node_modules/react",
    "npm_config_user_agent": "yarn/1.10.1 npm/? node/v12.10.0 darwin x64",
    "npm_config_ignore_scripts": "",
    "npm_config_version_git_sign": "",
    "npm_package_dependencies__testing_library_react": "^9.3.2",
    "npm_package_dependencies_mms_editor": "file:..",
    "SUDO_GID": "20",
    "npm_config_ignore_optional": "",
    "npm_config_init_version": "1.0.0",
    "npm_package_scripts_eject": "react-scripts eject",
    "npm_config_version_tag_prefix": "v",
    "npm_node_execpath": "/usr/local/bin/node",
    "_": "/Users/oguzgelal/Core/web/TOPTAL/marketmuse/mms-editor/example/node_modules/.bin/react-scripts",
    "BABEL_ENV": "development",
    "NODE_ENV": "development",
    "SKIP_PREFLIGHT_CHECK": "true",
    "NODE_PATH": "",
    "WEBPACK_DEV_SERVER": "true"
  },
  "userLimits": {
    "core_file_size_blocks": {
      "soft": 0,
      "hard": "unlimited"
    },
    "data_seg_size_kbytes": {
      "soft": "unlimited",
      "hard": "unlimited"
    },
    "file_size_blocks": {
      "soft": "unlimited",
      "hard": "unlimited"
    },
    "max_locked_memory_bytes": {
      "soft": "unlimited",
      "hard": "unlimited"
    },
    "max_memory_size_kbytes": {
      "soft": "unlimited",
      "hard": "unlimited"
    },
    "open_files": {
      "soft": 49152,
      "hard": "unlimited"
    },
    "stack_size_bytes": {
      "soft": 8388608,
      "hard": 67104768
    },
    "cpu_time_seconds": {
      "soft": "unlimited",
      "hard": "unlimited"
    },
    "max_user_processes": {
      "soft": 2784,
      "hard": 4176
    },
    "virtual_memory_kbytes": {
      "soft": "unlimited",
      "hard": "unlimited"
    }
  },
  "sharedObjects": [
    "/usr/local/bin/node",
    "/System/Library/Frameworks/CoreFoundation.framework/Versions/A/CoreFoundation",
    "/usr/lib/libSystem.B.dylib",
    "/usr/lib/libc++.1.dylib",
    "/usr/lib/libobjc.A.dylib",
    "/usr/lib/libfakelink.dylib",
    "/usr/lib/libDiagnosticMessagesClient.dylib",
    "/usr/lib/libicucore.A.dylib",
    "/usr/lib/libz.1.dylib",
    "/usr/lib/libc++abi.dylib",
    "/usr/lib/system/libcache.dylib",
    "/usr/lib/system/libcommonCrypto.dylib",
    "/usr/lib/system/libcompiler_rt.dylib",
    "/usr/lib/system/libcopyfile.dylib",
    "/usr/lib/system/libcorecrypto.dylib",
    "/usr/lib/system/libdispatch.dylib",
    "/usr/lib/system/libdyld.dylib",
    "/usr/lib/system/libkeymgr.dylib",
    "/usr/lib/system/liblaunch.dylib",
    "/usr/lib/system/libmacho.dylib",
    "/usr/lib/system/libquarantine.dylib",
    "/usr/lib/system/libremovefile.dylib",
    "/usr/lib/system/libsystem_asl.dylib",
    "/usr/lib/system/libsystem_blocks.dylib",
    "/usr/lib/system/libsystem_c.dylib",
    "/usr/lib/system/libsystem_configuration.dylib",
    "/usr/lib/system/libsystem_coreservices.dylib",
    "/usr/lib/system/libsystem_darwin.dylib",
    "/usr/lib/system/libsystem_dnssd.dylib",
    "/usr/lib/system/libsystem_featureflags.dylib",
    "/usr/lib/system/libsystem_info.dylib",
    "/usr/lib/system/libsystem_m.dylib",
    "/usr/lib/system/libsystem_malloc.dylib",
    "/usr/lib/system/libsystem_networkextension.dylib",
    "/usr/lib/system/libsystem_notify.dylib",
    "/usr/lib/system/libsystem_sandbox.dylib",
    "/usr/lib/system/libsystem_secinit.dylib",
    "/usr/lib/system/libsystem_kernel.dylib",
    "/usr/lib/system/libsystem_platform.dylib",
    "/usr/lib/system/libsystem_pthread.dylib",
    "/usr/lib/system/libsystem_symptoms.dylib",
    "/usr/lib/system/libsystem_trace.dylib",
    "/usr/lib/system/libunwind.dylib",
    "/usr/lib/system/libxpc.dylib",
    "/Users/oguzgelal/Core/web/TOPTAL/marketmuse/mms-editor/example/node_modules/fsevents/lib/binding/Release/node-v72-darwin-x64/fse.node",
    "/System/Library/Frameworks/CoreServices.framework/Versions/A/CoreServices",
    "/System/Library/Frameworks/CFNetwork.framework/Versions/A/CFNetwork",
    "/System/Library/Frameworks/CoreServices.framework/Versions/A/Frameworks/FSEvents.framework/Versions/A/FSEvents",
    "/System/Library/Frameworks/CoreServices.framework/Versions/A/Frameworks/CarbonCore.framework/Versions/A/CarbonCore",
    "/System/Library/Frameworks/CoreServices.framework/Versions/A/Frameworks/Metadata.framework/Versions/A/Metadata",
    "/System/Library/Frameworks/CoreServices.framework/Versions/A/Frameworks/OSServices.framework/Versions/A/OSServices",
    "/System/Library/Frameworks/CoreServices.framework/Versions/A/Frameworks/SearchKit.framework/Versions/A/SearchKit",
    "/System/Library/Frameworks/CoreServices.framework/Versions/A/Frameworks/AE.framework/Versions/A/AE",
    "/System/Library/Frameworks/CoreServices.framework/Versions/A/Frameworks/LaunchServices.framework/Versions/A/LaunchServices",
    "/System/Library/Frameworks/CoreServices.framework/Versions/A/Frameworks/DictionaryServices.framework/Versions/A/DictionaryServices",
    "/System/Library/Frameworks/CoreServices.framework/Versions/A/Frameworks/SharedFileList.framework/Versions/A/SharedFileList",
    "/System/Library/Frameworks/Foundation.framework/Versions/C/Foundation",
    "/System/Library/Frameworks/IOKit.framework/Versions/A/IOKit",
    "/System/Library/Frameworks/SystemConfiguration.framework/Versions/A/SystemConfiguration",
    "/System/Library/Frameworks/Security.framework/Versions/A/Security",
    "/usr/lib/libsqlite3.dylib",
    "/usr/lib/libxml2.2.dylib",
    "/usr/lib/libnetwork.dylib",
    "/usr/lib/libapple_nghttp2.dylib",
    "/usr/lib/libauto.dylib",
    "/usr/lib/libcompression.dylib",
    "/System/Library/Frameworks/DiskArbitration.framework/Versions/A/DiskArbitration",
    "/usr/lib/libarchive.2.dylib",
    "/usr/lib/liblangid.dylib",
    "/usr/lib/libCRFSuite.dylib",
    "/usr/lib/liblzma.5.dylib",
    "/usr/lib/libenergytrace.dylib",
    "/usr/lib/libbsm.0.dylib",
    "/usr/lib/system/libkxld.dylib",
    "/System/Library/PrivateFrameworks/AppleFSCompression.framework/Versions/A/AppleFSCompression",
    "/usr/lib/libcoretls.dylib",
    "/usr/lib/libcoretls_cfhelpers.dylib",
    "/usr/lib/libpam.2.dylib",
    "/usr/lib/libxar.1.dylib",
    "/usr/lib/libbz2.1.0.dylib",
    "/usr/lib/libiconv.2.dylib",
    "/usr/lib/libcharset.1.dylib",
    "/usr/lib/libpcap.A.dylib",
    "/System/Library/Frameworks/NetFS.framework/Versions/A/NetFS",
    "/System/Library/PrivateFrameworks/NetAuth.framework/Versions/A/NetAuth",
    "/System/Library/PrivateFrameworks/login.framework/Versions/A/Frameworks/loginsupport.framework/Versions/A/loginsupport",
    "/System/Library/PrivateFrameworks/TCC.framework/Versions/A/TCC",
    "/System/Library/PrivateFrameworks/CoreNLP.framework/Versions/A/CoreNLP",
    "/System/Library/PrivateFrameworks/MetadataUtilities.framework/Versions/A/MetadataUtilities",
    "/usr/lib/libmecabra.dylib",
    "/System/Library/Frameworks/Accelerate.framework/Versions/A/Accelerate",
    "/usr/lib/libmecab.dylib",
    "/usr/lib/libgermantok.dylib",
    "/usr/lib/libThaiTokenizer.dylib",
    "/usr/lib/libChineseTokenizer.dylib",
    "/System/Library/Frameworks/Accelerate.framework/Versions/A/Frameworks/vImage.framework/Versions/A/vImage",
    "/System/Library/Frameworks/Accelerate.framework/Versions/A/Frameworks/vecLib.framework/Versions/A/vecLib",
    "/System/Library/Frameworks/Accelerate.framework/Versions/A/Frameworks/vecLib.framework/Versions/A/libvMisc.dylib",
    "/System/Library/Frameworks/Accelerate.framework/Versions/A/Frameworks/vecLib.framework/Versions/A/libvDSP.dylib",
    "/System/Library/Frameworks/Accelerate.framework/Versions/A/Frameworks/vecLib.framework/Versions/A/libBLAS.dylib",
    "/System/Library/Frameworks/Accelerate.framework/Versions/A/Frameworks/vecLib.framework/Versions/A/libLAPACK.dylib",
    "/System/Library/Frameworks/Accelerate.framework/Versions/A/Frameworks/vecLib.framework/Versions/A/libLinearAlgebra.dylib",
    "/System/Library/Frameworks/Accelerate.framework/Versions/A/Frameworks/vecLib.framework/Versions/A/libSparseBLAS.dylib",
    "/System/Library/Frameworks/Accelerate.framework/Versions/A/Frameworks/vecLib.framework/Versions/A/libQuadrature.dylib",
    "/System/Library/Frameworks/Accelerate.framework/Versions/A/Frameworks/vecLib.framework/Versions/A/libBNNS.dylib",
    "/System/Library/Frameworks/Accelerate.framework/Versions/A/Frameworks/vecLib.framework/Versions/A/libSparse.dylib",
    "/System/Library/PrivateFrameworks/LanguageModeling.framework/Versions/A/LanguageModeling",
    "/System/Library/PrivateFrameworks/CoreEmoji.framework/Versions/A/CoreEmoji",
    "/System/Library/PrivateFrameworks/LinguisticData.framework/Versions/A/LinguisticData",
    "/System/Library/PrivateFrameworks/Lexicon.framework/Versions/A/Lexicon",
    "/usr/lib/libcmph.dylib",
    "/System/Library/Frameworks/OpenDirectory.framework/Versions/A/Frameworks/CFOpenDirectory.framework/Versions/A/CFOpenDirectory",
    "/System/Library/Frameworks/OpenDirectory.framework/Versions/A/OpenDirectory",
    "/System/Library/PrivateFrameworks/APFS.framework/Versions/A/APFS",
    "/System/Library/Frameworks/SecurityFoundation.framework/Versions/A/SecurityFoundation",
    "/usr/lib/libutil.dylib",
    "/System/Library/PrivateFrameworks/CoreServicesStore.framework/Versions/A/CoreServicesStore",
    "/System/Library/Frameworks/ServiceManagement.framework/Versions/A/ServiceManagement",
    "/System/Library/PrivateFrameworks/BackgroundTaskManagement.framework/Versions/A/BackgroundTaskManagement",
    "/usr/lib/libxslt.1.dylib"
  ]
}